{
    "ethnic": [
        {
            "id": "1",
            "label": "Kinh",
            "label gọi khác": "Việt"
        },
        {
            "id": "2",
            "label": "Tày",
            "label gọi khác": "Thổ, Ngạn, Phén, Thù Lao, Pa Dí, Tày Khao"
        },
        {
            "id": "3",
            "label": "Thái",
            "label gọi khác": "Tày Đăm, Tày Mười, Tày Thanh, Mán Thanh, Hàng Bông, Tày Mường, Pa Thay, Thổ Đà Bắc"
        },
        {
            "id": "4",
            "label": "Hoa",
            "label gọi khác": "Hán, Triều Châu, Phúc Kiến, Quảng Đông, Hải Nam, Hạ, Xạ Phạng"
        },
        {
            "id": "5",
            "label": "Khơ-me",
            "label gọi khác": "Cur, Cul, Cu, Thổ, Việt gốc Miên, Krôm"
        },
        {
            "id": "6",
            "label": "Mường",
            "label gọi khác": "Mol, Mual, Mọi, Mọi Bi, Ao Tá, Ậu Tá"
        },
        {
            "id": "7",
            "label": "Nùng",
            "label gọi khác": "Xuồng, Giang, Nùng An, Phàn Sinh, Nùng Cháo, Nùng Lòi, Quý Rim, Khèn Lài"
        },
        {
            "id": "8",
            "label": "HMông",
            "label gọi khác": "Mèo, Hoa, Mèo Xanh, Mèo Đỏ, Mèo Đen, Ná Mẻo, Mán Trắng"
        },
        {
            "id": "9",
            "label": "Dao",
            "label gọi khác": "Mán, Động, Trại, Xá, Dìu, Miên, Kiềm, Miền, Quần Trắng, Dao Đỏ, Quần Chẹt, Lô Giang, Dao Tiền, Thanh Y, Lan Tẻn, Đại Bản, Tiểu Bản, Cóc Ngáng, Cóc Mùn, Sơn Đầu"
        },
        {
            "id": "10",
            "label": "Gia-rai",
            "label gọi khác": "Giơ-rai, Tơ-buăn, Chơ-rai, Hơ-bau, Hđrung, Chor"
        },
        {
            "id": "11",
            "label": "Ngái",
            "label gọi khác": "Xín, Lê, Đản, Khách Gia"
        },
        {
            "id": "12",
            "label": "Ê-đê",
            "label gọi khác": "Ra-đê, Đê, Kpạ, A-đham, Krung, Ktul, Đliê Ruê, Blô, Epan, Mđhur, Bih"
        },
        {
            "id": "13",
            "label": "Ba na",
            "label gọi khác": "Giơ-lar. Tơ-lô, Giơ-lâng, Y-lăng, Rơ-ngao, Krem, Roh, ConKđe, A-la Công, Kpăng Công, Bơ-nâm"
        },
        {
            "id": "14",
            "label": "Xơ-Đăng",
            "label gọi khác": "Xơ-teng, Hđang, Tơ-đra, Mơ-nâm, Ha-lăng, Ca-dong, Kmrâng, ConLan, Bri-la, Tang"
        },
        {
            "id": "15",
            "label": "Sán Chay",
            "label gọi khác": "Cao Lan, Sán Chỉ, Mán Cao Lan, Hờn Bạn, Sơn Tử"
        },
        {
            "id": "16",
            "label": "Cơ-ho",
            "label gọi khác": "Xrê, Nốp, Tu-lốp, Cơ-don, Chil, Lat, Lach, Trinh"
        },
        {
            "id": "17",
            "label": "Chăm",
            "label gọi khác": "Chàm, Chiêm Thành, Hroi"
        },
        {
            "id": "18",
            "label": "Sán Dìu",
            "label gọi khác": "Sán Dẻo, Trại, Trại Đất, Mán, Quần Cộc"
        },
        {
            "id": "19",
            "label": "Hrê",
            "label gọi khác": "Chăm Rê, Chom, Krẹ Luỹ"
        },
        {
            "id": "20",
            "label": "Mnông",
            "label gọi khác": "Pnông, Nông, Pré, Bu-đâng, ĐiPri, Biat, Gar, Rơ-lam, Chil"
        },
        {
            "id": "21",
            "label": "Ra-glai",
            "label gọi khác": "Ra-clây, Rai, Noang, La-oang"
        },
        {
            "id": "22",
            "label": "Xtiêng",
            "label gọi khác": "Xa-điêng"
        },
        {
            "id": "23",
            "label": "Bru-Vân Kiều",
            "label gọi khác": "Bru, Vân Kiều, Măng Coong, Tri Khùa"
        },
        {
            "id": "24",
            "label": "Thổ",
            "label gọi khác": "Kẹo, Mọn, Cuối, Họ, Đan Lai, Ly Hà, Tày Pọng, Con Kha, Xá Lá Vàng"
        },
        {
            "id": "25",
            "label": "Giáy",
            "label gọi khác": "Nhắng, Dẩng, Pầu Thìn Nu Nà, Cùi Chu, Xa"
        },
        {
            "id": "26",
            "label": "Cơ-tu",
            "label gọi khác": "Ca-tu, Cao, Hạ, Phương, Ca-tang"
        },
        {
            "id": "27",
            "label": "Gié Triêng",
            "label gọi khác": "Đgiéh, Tareb, Giang Rẫy Pin, Triêng, Treng, Ta-riêng, Ve, Veh, La-ve, Ca-tang"
        },
        {
            "id": "28",
            "label": "Mạ",
            "label gọi khác": "Châu Mạ, Mạ Ngăn, Mạ Xóp, Mạ Tô, Mạ Krung"
        },
        {
            "id": "29",
            "label": "Khơ-mú",
            "label gọi khác": "Xá Cẩu, Mứn Xen, Pu Thênh, Tềnh, Tày Hay"
        },
        {
            "id": "30",
            "label": "Co",
            "label gọi khác": "Cor, Col, Cùa, Trầu"
        },
        {
            "id": "31",
            "label": "Tà-ôi",
            "label gọi khác": "Tôi-ôi, Pa-co, Pa-hi, Ba-hi"
        },
        {
            "id": "32",
            "label": "Chơ-ro",
            "label gọi khác": "Dơ-ro, Châu-ro"
        },
        {
            "id": "33",
            "label": "Kháng",
            "label gọi khác": "Xá Khao, Xá Súa, Xá Dón, Xá Dẩng, Xá Hốc, Xá Ái, Xá Bung, Quảng Lâm"
        },
        {
            "id": "34",
            "label": "Xinh-mun",
            "label gọi khác": "Puộc, Pụa"
        },
        {
            "id": "35",
            "label": "Hà Nhì",
            "label gọi khác": "U Ni, Xá U Ni"
        },
        {
            "id": "36",
            "label": "Chu ru",
            "label gọi khác": "Chơ-ru, Chu"
        },
        {
            "id": "37",
            "label": "Lào",
            "label gọi khác": "Là Bốc, Lào Nọi"
        },
        {
            "id": "38",
            "label": "La Chí",
            "label gọi khác": "Cù Tê, La Quả"
        },
        {
            "id": "39",
            "label": "La Ha",
            "label gọi khác": "Xá Khao, Khlá Phlạo"
        },
        {
            "id": "40",
            "label": "Phù Lá",
            "label gọi khác": "Bồ Khô Pạ, Mu Di Pạ Xá, Phó, Phổ, Va Xơ"
        },
        {
            "id": "41",
            "label": "La Hủ",
            "label gọi khác": "Lao, Pu Đang, Khù Xung, Cò Xung, Khả Quy"
        },
        {
            "id": "42",
            "label": "Lự",
            "label gọi khác": "Lừ, Nhuồn, Duôn"
        },
        {
            "id": "43",
            "label": "Lô Lô",
            "label gọi khác": "Mun Di"
        },
        {
            "id": "44",
            "label": "Chứt",
            "label gọi khác": "Sách, Máy, Rục, Mã-liêng, A-rem, Tu vang, Pa-leng, Xơ-Lang, Tơ-hung, Chà-củi, Tắc-củi, U-mo, Xá Lá Vàng"
        },
        {
            "id": "45",
            "label": "Mảng",
            "label gọi khác": "Mảng Ư, Xá Lá Vàng"
        },
        {
            "id": "46",
            "label": "Pà Thẻn",
            "label gọi khác": "Pà Hưng, Tống"
        },
        {
            "id": "47",
            "label": "Co Lao"
        },
        {
            "id": "48",
            "label": "Cống",
            "label gọi khác": "Xắm Khống, Mấng Nhé, Xá Xeng"
        },
        {
            "id": "49",
            "label": "Bố Y",
            "label gọi khác": "Chủng Chá, Trọng Gia, Tu Di, Tu Din"
        },
        {
            "id": "50",
            "label": "Si La",
            "label gọi khác": "Cù Dề Xừ, Khả pẻ"
        },
        {
            "id": "51",
            "label": "Pu Péo",
            "label gọi khác": "Ka Pèo, Pen Ti Lô Lô"
        },
        {
            "id": "52",
            "label": "Brâu",
            "label gọi khác": "Brao"
        },
        {
            "id": "53",
            "label": "Ơ Đu",
            "label gọi khác": "Tày Hạt"
        },
        {
            "id": "54",
            "label": "Rơ măm"
        },
        {
            "id": "55",
            "label": "Người nước ngoài"
        },
        {
            "id": "56",
            "label": "Không rõ"
        }
    ]
}